textual_fspicker/__init__.py
textual_fspicker/__main__.py
textual_fspicker/base_dialog.py
textual_fspicker/file_dialog.py
textual_fspicker/file_open.py
textual_fspicker/file_save.py
textual_fspicker/icons.py
textual_fspicker/parts/__init__.py
textual_fspicker/parts/current_directory.py
textual_fspicker/parts/directory_navigation.py
textual_fspicker/parts/drive_navigation.py
textual_fspicker/path_filters.py
textual_fspicker/path_maker.py
textual_fspicker/py.typed
textual_fspicker/safe_tests.py
textual_fspicker/select_directory.py
textual_fspicker/suggest_path.py
textual_fspicker-0.6.0.dist-info/WHEEL
textual_fspicker-0.6.0.dist-info/METADATA
textual_fspicker-0.6.0.dist-info/RECORD
